{"data_start_date": "2025-01-01", "total_posts": 16158, "nsfw_status": {"sfw": 15903, "nsfw": 255}, "flair": {"gmplw": 5085, "plw": 9242, "gmw": 1795}, "location": {"online": 14738, "online_and_offline": 195, "offline": 1198}, "play_by_post": 672, "one_shot": 1857, "identity": {"lfbtq": 3786, "fem": 75, "poc": 229, "accessible": 45}, "vtt": {"roll20": 2963, "foundry": 1876, "fantasy_grounds": 737, "tabletop_simulator": 240, "talespire": 67, "tableplop": 22, "one_more_multiverse": 3, "owlbear_rodeo": 617, "above_vtt": 34}, "day_of_week": {"monday": 2333, "tuesday": 2137, "wednesday": 2227, "thursday": 2308, "friday": 3026, "saturday": 4266, "sunday": 4340}, "game": {"40k": 83, "bitd": 11, "brp": 59, "coc": 155, "cofd": 17, "cyberpunk": 170, "dlc": 0, "dlr": 0, "dcc": 29, "dw": 36, "odnd": 25, "adnd": 25, "bx": 45, "dnd2e": 18, "3e": 25, "3.5": 84, "4e": 70, "5e": 11040, "1dnd": 87, "earthdawn": 0, "fate": 66, "feast": 8, "flexible": 3127, "fws": 0, "gurps": 37, "l5r": 1, "mcc": 2, "motw": 46, "mm3": 45, "numenera": 4, "pf2e": 936, "pf1e": 215, "swade": 13, "swd": 18, "sr3": 0, "sr4": 0, "sr5": 10, "sr6": 5, "starfinder": 62, "swrpg": 58, "swn": 0, "wod": 284}, "timezone": {"americas": {"GMT-3": 72, "GMT-4": 230, "GMT-5": 5211, "GMT-6": 2103, "GMT-7": 564, "GMT-8": 1460, "GMT-9": 4}, "europe": {"GMT-1": 4, "GMT+0": 1031, "GMT+1": 906, "GMT+2": 431, "GMT+3": 101}, "australia": {"GMT+8": 115, "GMT+9": 9, "GMT+9:30": 4, "GMT+10": 163, "GMT+10:30": 7, "GMT+11": 37}}, "generated_time": "2025-07-03 23:59:09"}