{"data_start_date": "2026-01-01", "total_posts": 40125, "nsfw_status": {"sfw": 39310, "nsfw": 815}, "flair": {"gmplw": 10416, "plw": 20172, "gmw": 4340}, "location": {"online": 37100, "online_and_offline": 308, "offline": 2615}, "play_by_post": 1827, "one_shot": 4265, "identity": {"lfbtq": 9678, "fem": 163, "poc": 550, "accessible": 113}, "vtt": {"roll20": 7465, "foundry": 5602, "fantasy_grounds": 2072, "tabletop_simulator": 799, "talespire": 136, "tableplop": 11, "one_more_multiverse": 31, "owlbear_rodeo": 1746, "above_vtt": 107}, "day_of_week": {"monday": 5922, "tuesday": 5151, "wednesday": 5784, "thursday": 5837, "friday": 7143, "saturday": 10327, "sunday": 10663}, "game": {"40k": 197, "bitd": 12, "brp": 171, "coc": 474, "cofd": 62, "cyberpunk": 503, "dlc": 3, "dlr": 0, "dcc": 89, "dw": 122, "odnd": 83, "adnd": 109, "bx": 182, "dnd2e": 41, "3e": 82, "3.5": 476, "4e": 181, "5e": 24536, "1dnd": 0, "earthdawn": 29, "fate": 165, "feast": 11, "flexible": 9177, "fws": 0, "gurps": 100, "l5r": 11, "mcc": 0, "motw": 63, "mm3": 96, "numenera": 4, "pf2e": 2141, "pf1e": 628, "swade": 10, "swd": 54, "sr3": 0, "sr4": 0, "sr5": 2, "sr6": 7, "starfinder": 270, "swrpg": 121, "swn": 1, "wod": 1003}, "timezone": {"americas": {"GMT-3": 183, "GMT-4": 1065, "GMT-5": 13268, "GMT-6": 5595, "GMT-7": 1508, "GMT-8": 3683, "GMT-9": 22}, "europe": {"GMT-1": 4, "GMT+0": 2485, "GMT+1": 2690, "GMT+2": 1630, "GMT+3": 238}, "australia": {"GMT+8": 375, "GMT+9": 49, "GMT+9:30": 39, "GMT+10": 387, "GMT+10:30": 33, "GMT+11": 111}}, "generated_time": "2026-07-16 23:59:11"}