{"data_start_date": "2024-01-01", "total_posts": 15064, "nsfw_status": {"sfw": 14858, "nsfw": 206}, "flair": {"gmplw": 4902, "plw": 8425, "gmw": 1701}, "location": {"online": 13660, "online_and_offline": 196, "offline": 1181}, "play_by_post": 669, "one_shot": 1698, "identity": {"lfbtq": 3475, "fem": 64, "poc": 224, "accessible": 68}, "vtt": {"roll20": 2906, "foundry": 1704, "fantasy_grounds": 689, "tabletop_simulator": 233, "talespire": 86, "tableplop": 23, "one_more_multiverse": 5, "owlbear_rodeo": 363, "above_vtt": 30}, "day_of_week": {"monday": 2313, "tuesday": 2018, "wednesday": 2138, "thursday": 2261, "friday": 2771, "saturday": 3725, "sunday": 3837}, "game": {"40k": 84, "bitd": 29, "brp": 25, "coc": 176, "cofd": 18, "cyberpunk": 180, "dlc": 1, "dlr": 1, "dcc": 14, "dw": 28, "odnd": 37, "adnd": 39, "bx": 54, "dnd2e": 17, "3e": 12, "3.5": 110, "4e": 73, "5e": 10595, "1dnd": 8, "earthdawn": 3, "fate": 53, "feast": 0, "flexible": 2562, "fws": 0, "gurps": 42, "l5r": 8, "mcc": 1, "motw": 50, "mm3": 27, "numenera": 13, "pf2e": 902, "pf1e": 258, "swade": 47, "swd": 16, "sr3": 2, "sr4": 2, "sr5": 8, "sr6": 6, "starfinder": 55, "swrpg": 63, "swn": 2, "wod": 189}, "timezone": {"americas": {"GMT-3": 100, "GMT-4": 172, "GMT-5": 4775, "GMT-6": 1933, "GMT-7": 649, "GMT-8": 1330, "GMT-9": 4}, "europe": {"GMT-1": 1, "GMT+0": 1117, "GMT+1": 782, "GMT+2": 387, "GMT+3": 107}, "australia": {"GMT+8": 103, "GMT+9": 13, "GMT+9:30": 8, "GMT+10": 167, "GMT+10:30": 7, "GMT+11": 54}}, "generated_time": "2024-06-06 23:59:14"}