{"data_start_date": "2025-01-01", "total_posts": 33326, "nsfw_status": {"sfw": 32720, "nsfw": 606}, "flair": {"gmplw": 10150, "plw": 19085, "gmw": 3768}, "location": {"online": 30559, "online_and_offline": 373, "offline": 2339}, "play_by_post": 1410, "one_shot": 3860, "identity": {"lfbtq": 8062, "fem": 142, "poc": 435, "accessible": 102}, "vtt": {"roll20": 6173, "foundry": 4110, "fantasy_grounds": 1570, "tabletop_simulator": 527, "talespire": 160, "tableplop": 30, "one_more_multiverse": 6, "owlbear_rodeo": 1210, "above_vtt": 58}, "day_of_week": {"monday": 5015, "tuesday": 4380, "wednesday": 4635, "thursday": 4888, "friday": 6253, "saturday": 8678, "sunday": 8859}, "game": {"40k": 199, "bitd": 18, "brp": 121, "coc": 332, "cofd": 46, "cyberpunk": 312, "dlc": 0, "dlr": 0, "dcc": 51, "dw": 80, "odnd": 72, "adnd": 59, "bx": 84, "dnd2e": 47, "3e": 40, "3.5": 193, "4e": 124, "5e": 22200, "1dnd": 87, "earthdawn": 2, "fate": 128, "feast": 18, "flexible": 6924, "fws": 0, "gurps": 82, "l5r": 3, "mcc": 2, "motw": 89, "mm3": 83, "numenera": 15, "pf2e": 1886, "pf1e": 523, "swade": 17, "swd": 33, "sr3": 0, "sr4": 0, "sr5": 20, "sr6": 8, "starfinder": 162, "swrpg": 141, "swn": 0, "wod": 553}, "timezone": {"americas": {"GMT-3": 163, "GMT-4": 549, "GMT-5": 10706, "GMT-6": 4357, "GMT-7": 1112, "GMT-8": 2971, "GMT-9": 11}, "europe": {"GMT-1": 8, "GMT+0": 1989, "GMT+1": 1930, "GMT+2": 1049, "GMT+3": 225}, "australia": {"GMT+8": 291, "GMT+9": 14, "GMT+9:30": 16, "GMT+10": 396, "GMT+10:30": 11, "GMT+11": 101}}, "generated_time": "2025-12-20 23:59:12"}