{"data_start_date": "2021-05-20", "total_posts": 161054, "nsfw_status": {"sfw": 158768, "nsfw": 2286}, "flair": {"gmplw": 53987, "plw": 87694, "gmw": 19092}, "location": {"online": 146153, "online_and_offline": 2024, "offline": 12648}, "play_by_post": 7280, "one_shot": 18211, "identity": {"lfbtq": 35396, "fem": 590, "poc": 2525, "accessible": 528}, "vtt": {"roll20": 33609, "foundry": 14574, "fantasy_grounds": 7709, "tabletop_simulator": 2384, "talespire": 728, "tableplop": 112, "one_more_multiverse": 101, "owlbear_rodeo": 2214, "above_vtt": 174}, "day_of_week": {"monday": 23058, "tuesday": 21318, "wednesday": 22004, "thursday": 22763, "friday": 29281, "saturday": 39047, "sunday": 39890}, "game": {"40k": 905, "bitd": 281, "brp": 270, "coc": 1636, "cofd": 276, "cyberpunk": 1524, "dlc": 22, "dlr": 16, "dcc": 252, "dw": 416, "odnd": 283, "adnd": 256, "bx": 402, "dnd2e": 171, "3e": 320, "3.5": 1198, "4e": 604, "5e": 117090, "1dnd": 190, "earthdawn": 13, "fate": 601, "feast": 22, "flexible": 27983, "fws": 11, "gurps": 405, "l5r": 99, "mcc": 9, "motw": 559, "mm3": 357, "numenera": 139, "pf2e": 8087, "pf1e": 3024, "swade": 375, "swd": 244, "sr3": 17, "sr4": 32, "sr5": 218, "sr6": 54, "starfinder": 913, "swrpg": 736, "swn": 19, "wod": 2156}, "timezone": {"americas": {"GMT-3": 856, "GMT-4": 2742, "GMT-5": 51381, "GMT-6": 20220, "GMT-7": 6237, "GMT-8": 15122, "GMT-9": 42}, "europe": {"GMT-1": 22, "GMT+0": 10802, "GMT+1": 8945, "GMT+2": 4937, "GMT+3": 1404}, "australia": {"GMT+8": 1204, "GMT+9": 130, "GMT+9:30": 77, "GMT+10": 1713, "GMT+10:30": 49, "GMT+11": 361}}, "generated_time": "2025-07-22 23:59:37"}