{"data_start_date": "2024-01-01", "total_posts": 3296, "nsfw_status": {"sfw": 3250, "nsfw": 46}, "flair": {"gmplw": 1064, "plw": 1855, "gmw": 369}, "location": {"online": 2945, "online_and_offline": 64, "offline": 282}, "play_by_post": 124, "one_shot": 363, "identity": {"lfbtq": 763, "fem": 10, "poc": 55, "accessible": 18}, "vtt": {"roll20": 637, "foundry": 371, "fantasy_grounds": 124, "tabletop_simulator": 51, "talespire": 17, "tableplop": 4, "one_more_multiverse": 1, "owlbear_rodeo": 78, "above_vtt": 8}, "day_of_week": {"monday": 476, "tuesday": 421, "wednesday": 489, "thursday": 509, "friday": 622, "saturday": 851, "sunday": 872}, "game": {"40k": 15, "bitd": 7, "brp": 0, "coc": 51, "cofd": 5, "cyberpunk": 47, "dlc": 0, "dlr": 0, "dcc": 1, "dw": 5, "odnd": 12, "adnd": 12, "bx": 15, "dnd2e": 3, "3e": 2, "3.5": 34, "4e": 14, "5e": 2365, "1dnd": 1, "earthdawn": 0, "fate": 8, "feast": 0, "flexible": 476, "fws": 0, "gurps": 7, "l5r": 1, "mcc": 1, "motw": 11, "mm3": 4, "numenera": 4, "pf2e": 191, "pf1e": 72, "swade": 4, "swd": 4, "sr3": 1, "sr4": 1, "sr5": 3, "sr6": 1, "starfinder": 7, "swrpg": 20, "swn": 0, "wod": 32}, "timezone": {"americas": {"GMT-3": 19, "GMT-4": 10, "GMT-5": 1052, "GMT-6": 419, "GMT-7": 119, "GMT-8": 302, "GMT-9": 0}, "europe": {"GMT-1": 1, "GMT+0": 267, "GMT+1": 181, "GMT+2": 64, "GMT+3": 15}, "australia": {"GMT+8": 21, "GMT+9": 2, "GMT+9:30": 1, "GMT+10": 35, "GMT+10:30": 4, "GMT+11": 20}}, "generated_time": "2024-02-02 23:59:26"}