{"data_start_date": "2021-05-20", "total_posts": 157488, "nsfw_status": {"sfw": 155269, "nsfw": 2219}, "flair": {"gmplw": 52929, "plw": 85584, "gmw": 18703}, "location": {"online": 142897, "online_and_offline": 1985, "offline": 12381}, "play_by_post": 7139, "one_shot": 17736, "identity": {"lfbtq": 34582, "fem": 578, "poc": 2480, "accessible": 517}, "vtt": {"roll20": 32898, "foundry": 14161, "fantasy_grounds": 7546, "tabletop_simulator": 2331, "talespire": 712, "tableplop": 112, "one_more_multiverse": 101, "owlbear_rodeo": 2095, "above_vtt": 162}, "day_of_week": {"monday": 22564, "tuesday": 20881, "wednesday": 21492, "thursday": 22256, "friday": 28654, "saturday": 38167, "sunday": 38981}, "game": {"40k": 886, "bitd": 280, "brp": 260, "coc": 1603, "cofd": 274, "cyberpunk": 1483, "dlc": 22, "dlr": 16, "dcc": 243, "dw": 407, "odnd": 274, "adnd": 250, "bx": 391, "dnd2e": 168, "3e": 315, "3.5": 1178, "4e": 579, "5e": 114703, "1dnd": 190, "earthdawn": 13, "fate": 589, "feast": 21, "flexible": 27155, "fws": 11, "gurps": 398, "l5r": 99, "mcc": 9, "motw": 549, "mm3": 349, "numenera": 138, "pf2e": 7906, "pf1e": 2988, "swade": 375, "swd": 237, "sr3": 17, "sr4": 32, "sr5": 209, "sr6": 54, "starfinder": 896, "swrpg": 723, "swn": 19, "wod": 2112}, "timezone": {"americas": {"GMT-3": 839, "GMT-4": 2667, "GMT-5": 50281, "GMT-6": 19724, "GMT-7": 6101, "GMT-8": 14803, "GMT-9": 41}, "europe": {"GMT-1": 22, "GMT+0": 10631, "GMT+1": 8739, "GMT+2": 4815, "GMT+3": 1380}, "australia": {"GMT+8": 1172, "GMT+9": 129, "GMT+9:30": 76, "GMT+10": 1670, "GMT+10:30": 49, "GMT+11": 360}}, "generated_time": "2025-06-11 23:59:13"}