{"data_start_date": "2024-01-01", "total_posts": 11601, "nsfw_status": {"sfw": 11447, "nsfw": 154}, "flair": {"gmplw": 3785, "plw": 6501, "gmw": 1288}, "location": {"online": 10487, "online_and_offline": 156, "offline": 938}, "play_by_post": 521, "one_shot": 1270, "identity": {"lfbtq": 2669, "fem": 45, "poc": 169, "accessible": 57}, "vtt": {"roll20": 2204, "foundry": 1276, "fantasy_grounds": 520, "tabletop_simulator": 178, "talespire": 61, "tableplop": 19, "one_more_multiverse": 3, "owlbear_rodeo": 281, "above_vtt": 21}, "day_of_week": {"monday": 1778, "tuesday": 1584, "wednesday": 1665, "thursday": 1779, "friday": 2133, "saturday": 2845, "sunday": 2986}, "game": {"40k": 61, "bitd": 21, "brp": 15, "coc": 145, "cofd": 11, "cyberpunk": 143, "dlc": 1, "dlr": 1, "dcc": 13, "dw": 20, "odnd": 32, "adnd": 36, "bx": 43, "dnd2e": 12, "3e": 6, "3.5": 78, "4e": 54, "5e": 8209, "1dnd": 8, "earthdawn": 2, "fate": 36, "feast": 0, "flexible": 1908, "fws": 0, "gurps": 29, "l5r": 8, "mcc": 1, "motw": 44, "mm3": 13, "numenera": 8, "pf2e": 704, "pf1e": 219, "swade": 37, "swd": 13, "sr3": 1, "sr4": 2, "sr5": 7, "sr6": 4, "starfinder": 39, "swrpg": 47, "swn": 2, "wod": 146}, "timezone": {"americas": {"GMT-3": 71, "GMT-4": 91, "GMT-5": 3702, "GMT-6": 1456, "GMT-7": 471, "GMT-8": 1034, "GMT-9": 4}, "europe": {"GMT-1": 1, "GMT+0": 928, "GMT+1": 592, "GMT+2": 266, "GMT+3": 66}, "australia": {"GMT+8": 79, "GMT+9": 10, "GMT+9:30": 6, "GMT+10": 120, "GMT+10:30": 6, "GMT+11": 51}}, "generated_time": "2024-04-30 23:59:55"}