{"data_start_date": "2021-05-20", "total_posts": 176048, "nsfw_status": {"sfw": 173447, "nsfw": 2601}, "flair": {"gmplw": 58393, "plw": 96283, "gmw": 20812}, "location": {"online": 159983, "online_and_offline": 2165, "offline": 13646}, "play_by_post": 7923, "one_shot": 19962, "identity": {"lfbtq": 39161, "fem": 652, "poc": 2705, "accessible": 578}, "vtt": {"roll20": 36391, "foundry": 16535, "fantasy_grounds": 8439, "tabletop_simulator": 2642, "talespire": 804, "tableplop": 120, "one_more_multiverse": 104, "owlbear_rodeo": 2726, "above_vtt": 194}, "day_of_week": {"monday": 25439, "tuesday": 23291, "wednesday": 24093, "thursday": 25009, "friday": 32097, "saturday": 42904, "sunday": 43800}, "game": {"40k": 1005, "bitd": 287, "brp": 328, "coc": 1793, "cofd": 304, "cyberpunk": 1648, "dlc": 22, "dlr": 16, "dcc": 273, "dw": 457, "odnd": 322, "adnd": 288, "bx": 433, "dnd2e": 199, "3e": 333, "3.5": 1295, "4e": 645, "5e": 126777, "1dnd": 190, "earthdawn": 15, "fate": 658, "feast": 32, "flexible": 31308, "fws": 11, "gurps": 446, "l5r": 100, "mcc": 9, "motw": 600, "mm3": 389, "numenera": 148, "pf2e": 8921, "pf1e": 3304, "swade": 379, "swd": 254, "sr3": 17, "sr4": 32, "sr5": 225, "sr6": 57, "starfinder": 997, "swrpg": 814, "swn": 19, "wod": 2397}, "timezone": {"americas": {"GMT-3": 936, "GMT-4": 3022, "GMT-5": 56154, "GMT-6": 22169, "GMT-7": 6699, "GMT-8": 16413, "GMT-9": 49}, "europe": {"GMT-1": 26, "GMT+0": 11651, "GMT+1": 9847, "GMT+2": 5499, "GMT+3": 1516}, "australia": {"GMT+8": 1365, "GMT+9": 135, "GMT+9:30": 89, "GMT+10": 1910, "GMT+10:30": 53, "GMT+11": 420}}, "generated_time": "2025-12-14 23:59:16"}