{"data_start_date": "2024-01-01", "total_posts": 33428, "nsfw_status": {"sfw": 32905, "nsfw": 523}, "flair": {"gmplw": 10949, "plw": 18615, "gmw": 3792}, "location": {"online": 30500, "online_and_offline": 390, "offline": 2481}, "play_by_post": 1362, "one_shot": 3829, "identity": {"lfbtq": 7583, "fem": 126, "poc": 529, "accessible": 141}, "vtt": {"roll20": 6324, "foundry": 3778, "fantasy_grounds": 1454, "tabletop_simulator": 493, "talespire": 174, "tableplop": 49, "one_more_multiverse": 11, "owlbear_rodeo": 911, "above_vtt": 78}, "day_of_week": {"monday": 4886, "tuesday": 4363, "wednesday": 4671, "thursday": 4836, "friday": 6191, "saturday": 7974, "sunday": 8399}, "game": {"40k": 195, "bitd": 39, "brp": 83, "coc": 372, "cofd": 50, "cyberpunk": 374, "dlc": 1, "dlr": 1, "dcc": 43, "dw": 81, "odnd": 64, "adnd": 58, "bx": 87, "dnd2e": 29, "3e": 65, "3.5": 247, "4e": 129, "5e": 23278, "1dnd": 88, "earthdawn": 4, "fate": 115, "feast": 9, "flexible": 5961, "fws": 0, "gurps": 103, "l5r": 12, "mcc": 2, "motw": 104, "mm3": 58, "numenera": 40, "pf2e": 2090, "pf1e": 515, "swade": 54, "swd": 36, "sr3": 2, "sr4": 3, "sr5": 9, "sr6": 6, "starfinder": 145, "swrpg": 123, "swn": 3, "wod": 422}, "timezone": {"americas": {"GMT-3": 227, "GMT-4": 554, "GMT-5": 10614, "GMT-6": 4188, "GMT-7": 1356, "GMT-8": 2924, "GMT-9": 6}, "europe": {"GMT-1": 3, "GMT+0": 2286, "GMT+1": 1898, "GMT+2": 1052, "GMT+3": 311}, "australia": {"GMT+8": 263, "GMT+9": 33, "GMT+9:30": 20, "GMT+10": 423, "GMT+10:30": 11, "GMT+11": 84}}, "generated_time": "2024-12-30 23:59:07"}