{"data_start_date": "2025-01-01", "total_posts": 30260, "nsfw_status": {"sfw": 29709, "nsfw": 551}, "flair": {"gmplw": 9249, "plw": 17337, "gmw": 3363}, "location": {"online": 27719, "online_and_offline": 334, "offline": 2157}, "play_by_post": 1302, "one_shot": 3514, "identity": {"lfbtq": 7297, "fem": 132, "poc": 409, "accessible": 95}, "vtt": {"roll20": 5623, "foundry": 3756, "fantasy_grounds": 1422, "tabletop_simulator": 469, "talespire": 134, "tableplop": 29, "one_more_multiverse": 6, "owlbear_rodeo": 1088, "above_vtt": 56}, "day_of_week": {"monday": 4500, "tuesday": 3995, "wednesday": 4185, "thursday": 4414, "friday": 5691, "saturday": 7896, "sunday": 8089}, "game": {"40k": 173, "bitd": 18, "brp": 104, "coc": 305, "cofd": 42, "cyberpunk": 283, "dlc": 0, "dlr": 0, "dcc": 44, "dw": 72, "odnd": 61, "adnd": 54, "bx": 77, "dnd2e": 41, "3e": 37, "3.5": 173, "4e": 114, "5e": 20186, "1dnd": 87, "earthdawn": 2, "fate": 120, "feast": 18, "flexible": 6286, "fws": 0, "gurps": 72, "l5r": 2, "mcc": 2, "motw": 79, "mm3": 72, "numenera": 11, "pf2e": 1751, "pf1e": 466, "swade": 17, "swd": 30, "sr3": 0, "sr4": 0, "sr5": 20, "sr6": 8, "starfinder": 150, "swrpg": 121, "swn": 0, "wod": 509}, "timezone": {"americas": {"GMT-3": 153, "GMT-4": 525, "GMT-5": 9696, "GMT-6": 3958, "GMT-7": 1020, "GMT-8": 2682, "GMT-9": 11}, "europe": {"GMT-1": 5, "GMT+0": 1774, "GMT+1": 1738, "GMT+2": 986, "GMT+3": 209}, "australia": {"GMT+8": 261, "GMT+9": 12, "GMT+9:30": 12, "GMT+10": 365, "GMT+10:30": 10, "GMT+11": 82}}, "generated_time": "2025-11-14 23:59:17"}