{"data_start_date": "2021-05-20", "total_posts": 109586, "nsfw_status": {"sfw": 108109, "nsfw": 1477}, "flair": {"gmplw": 37401, "plw": 58719, "gmw": 13297}, "location": {"online": 99205, "online_and_offline": 1410, "offline": 8828}, "play_by_post": 5159, "one_shot": 12298, "identity": {"lfbtq": 23586, "fem": 384, "poc": 1741, "accessible": 334}, "vtt": {"roll20": 23955, "foundry": 8704, "fantasy_grounds": 5428, "tabletop_simulator": 1631, "talespire": 478, "tableplop": 41, "one_more_multiverse": 87, "owlbear_rodeo": 624, "above_vtt": 58}, "day_of_week": {"monday": 15598, "tuesday": 14590, "wednesday": 14841, "thursday": 15343, "friday": 19705, "saturday": 26335, "sunday": 26628}, "game": {"40k": 614, "bitd": 230, "brp": 125, "coc": 1093, "cofd": 208, "cyberpunk": 961, "dlc": 21, "dlr": 15, "dcc": 179, "dw": 296, "odnd": 188, "adnd": 170, "bx": 264, "dnd2e": 124, "3e": 227, "3.5": 852, "4e": 394, "5e": 81480, "1dnd": 15, "earthdawn": 9, "fate": 415, "feast": 5, "flexible": 18487, "fws": 11, "gurps": 263, "l5r": 86, "mcc": 5, "motw": 407, "mm3": 249, "numenera": 94, "pf2e": 4965, "pf1e": 2272, "swade": 308, "swd": 185, "sr3": 15, "sr4": 29, "sr5": 196, "sr6": 43, "starfinder": 695, "swrpg": 549, "swn": 16, "wod": 1427}, "timezone": {"americas": {"GMT-3": 548, "GMT-4": 1918, "GMT-5": 34941, "GMT-6": 13661, "GMT-7": 4234, "GMT-8": 10554, "GMT-9": 32}, "europe": {"GMT-1": 15, "GMT+0": 7390, "GMT+1": 6030, "GMT+2": 3404, "GMT+3": 982}, "australia": {"GMT+8": 814, "GMT+9": 88, "GMT+9:30": 53, "GMT+10": 1098, "GMT+10:30": 31, "GMT+11": 237}}, "generated_time": "2023-12-29 23:59:42"}