{"data_start_date": "2021-05-20", "total_posts": 119452, "nsfw_status": {"sfw": 117849, "nsfw": 1603}, "flair": {"gmplw": 40629, "plw": 64255, "gmw": 14374}, "location": {"online": 108124, "online_and_offline": 1546, "offline": 9621}, "play_by_post": 5593, "one_shot": 13380, "identity": {"lfbtq": 25860, "fem": 419, "poc": 1887, "accessible": 385}, "vtt": {"roll20": 25802, "foundry": 9761, "fantasy_grounds": 5856, "tabletop_simulator": 1782, "talespire": 529, "tableplop": 55, "one_more_multiverse": 89, "owlbear_rodeo": 868, "above_vtt": 78}, "day_of_week": {"monday": 17102, "tuesday": 15935, "wednesday": 16266, "thursday": 16875, "friday": 21513, "saturday": 28785, "sunday": 29156}, "game": {"40k": 666, "bitd": 249, "brp": 138, "coc": 1220, "cofd": 217, "cyberpunk": 1086, "dlc": 22, "dlr": 16, "dcc": 187, "dw": 314, "odnd": 216, "adnd": 202, "bx": 299, "dnd2e": 134, "3e": 234, "3.5": 927, "4e": 442, "5e": 88504, "1dnd": 22, "earthdawn": 11, "fate": 445, "feast": 5, "flexible": 20074, "fws": 11, "gurps": 286, "l5r": 89, "mcc": 6, "motw": 443, "mm3": 260, "numenera": 102, "pf2e": 5571, "pf1e": 2449, "swade": 345, "swd": 194, "sr3": 16, "sr4": 30, "sr5": 201, "sr6": 46, "starfinder": 723, "swrpg": 588, "swn": 18, "wod": 1557}, "timezone": {"americas": {"GMT-3": 610, "GMT-4": 1977, "GMT-5": 38087, "GMT-6": 14907, "GMT-7": 4612, "GMT-8": 11453, "GMT-9": 34}, "europe": {"GMT-1": 16, "GMT+0": 8199, "GMT+1": 6545, "GMT+2": 3600, "GMT+3": 1036}, "australia": {"GMT+8": 883, "GMT+9": 95, "GMT+9:30": 56, "GMT+10": 1188, "GMT+10:30": 37, "GMT+11": 287}}, "generated_time": "2024-04-10 23:59:23"}