{"data_start_date": "2021-05-20", "total_posts": 126305, "nsfw_status": {"sfw": 124595, "nsfw": 1710}, "flair": {"gmplw": 42809, "plw": 68102, "gmw": 15186}, "location": {"online": 114375, "online_and_offline": 1623, "offline": 10135}, "play_by_post": 5885, "one_shot": 14199, "identity": {"lfbtq": 27443, "fem": 455, "poc": 1988, "accessible": 411}, "vtt": {"roll20": 27172, "foundry": 10604, "fantasy_grounds": 6208, "tabletop_simulator": 1897, "talespire": 579, "tableplop": 67, "one_more_multiverse": 94, "owlbear_rodeo": 1032, "above_vtt": 92}, "day_of_week": {"monday": 18131, "tuesday": 16841, "wednesday": 17206, "thursday": 17812, "friday": 22778, "saturday": 30437, "sunday": 30870}, "game": {"40k": 709, "bitd": 259, "brp": 154, "coc": 1284, "cofd": 229, "cyberpunk": 1163, "dlc": 22, "dlr": 16, "dcc": 202, "dw": 326, "odnd": 225, "adnd": 211, "bx": 318, "dnd2e": 142, "3e": 246, "3.5": 977, "4e": 469, "5e": 93222, "1dnd": 24, "earthdawn": 12, "fate": 474, "feast": 5, "flexible": 21356, "fws": 11, "gurps": 307, "l5r": 94, "mcc": 6, "motw": 459, "mm3": 279, "numenera": 108, "pf2e": 5985, "pf1e": 2551, "swade": 356, "swd": 205, "sr3": 17, "sr4": 32, "sr5": 204, "sr6": 49, "starfinder": 755, "swrpg": 625, "swn": 18, "wod": 1638}, "timezone": {"americas": {"GMT-3": 667, "GMT-4": 2134, "GMT-5": 40260, "GMT-6": 15769, "GMT-7": 4946, "GMT-8": 12051, "GMT-9": 37}, "europe": {"GMT-1": 16, "GMT+0": 8589, "GMT+1": 6897, "GMT+2": 3838, "GMT+3": 1112}, "australia": {"GMT+8": 927, "GMT+9": 106, "GMT+9:30": 62, "GMT+10": 1280, "GMT+10:30": 38, "GMT+11": 292}}, "generated_time": "2024-06-22 23:59:18"}