{"data_start_date": "2021-05-20", "total_posts": 152103, "nsfw_status": {"sfw": 149964, "nsfw": 2139}, "flair": {"gmplw": 51280, "plw": 82427, "gmw": 18136}, "location": {"online": 138007, "online_and_offline": 1899, "offline": 11981}, "play_by_post": 6936, "one_shot": 17154, "identity": {"lfbtq": 33322, "fem": 559, "poc": 2412, "accessible": 495}, "vtt": {"roll20": 31917, "foundry": 13573, "fantasy_grounds": 7261, "tabletop_simulator": 2260, "talespire": 695, "tableplop": 104, "one_more_multiverse": 101, "owlbear_rodeo": 1891, "above_vtt": 153}, "day_of_week": {"monday": 21815, "tuesday": 20222, "wednesday": 20774, "thursday": 21499, "friday": 27693, "saturday": 36801, "sunday": 37566}, "game": {"40k": 867, "bitd": 277, "brp": 241, "coc": 1553, "cofd": 266, "cyberpunk": 1417, "dlc": 22, "dlr": 16, "dcc": 233, "dw": 396, "odnd": 265, "adnd": 245, "bx": 370, "dnd2e": 166, "3e": 308, "3.5": 1141, "4e": 552, "5e": 111081, "1dnd": 190, "earthdawn": 13, "fate": 563, "feast": 19, "flexible": 26076, "fws": 11, "gurps": 384, "l5r": 99, "mcc": 9, "motw": 534, "mm3": 335, "numenera": 136, "pf2e": 7602, "pf1e": 2927, "swade": 372, "swd": 231, "sr3": 17, "sr4": 32, "sr5": 207, "sr6": 50, "starfinder": 881, "swrpg": 695, "swn": 19, "wod": 2019}, "timezone": {"americas": {"GMT-3": 819, "GMT-4": 2569, "GMT-5": 48569, "GMT-6": 19017, "GMT-7": 5921, "GMT-8": 14331, "GMT-9": 39}, "europe": {"GMT-1": 20, "GMT+0": 10371, "GMT+1": 8411, "GMT+2": 4629, "GMT+3": 1335}, "australia": {"GMT+8": 1129, "GMT+9": 126, "GMT+9:30": 73, "GMT+10": 1599, "GMT+10:30": 49, "GMT+11": 357}}, "generated_time": "2025-04-10 23:59:12"}