{"data_start_date": "2021-05-20", "total_posts": 127005, "nsfw_status": {"sfw": 125275, "nsfw": 1730}, "flair": {"gmplw": 43039, "plw": 68480, "gmw": 15277}, "location": {"online": 115002, "online_and_offline": 1628, "offline": 10202}, "play_by_post": 5906, "one_shot": 14283, "identity": {"lfbtq": 27596, "fem": 460, "poc": 1997, "accessible": 412}, "vtt": {"roll20": 27320, "foundry": 10684, "fantasy_grounds": 6234, "tabletop_simulator": 1906, "talespire": 582, "tableplop": 68, "one_more_multiverse": 94, "owlbear_rodeo": 1058, "above_vtt": 92}, "day_of_week": {"monday": 18229, "tuesday": 16937, "wednesday": 17323, "thursday": 17918, "friday": 22905, "saturday": 30599, "sunday": 31058}, "game": {"40k": 714, "bitd": 259, "brp": 157, "coc": 1287, "cofd": 230, "cyberpunk": 1169, "dlc": 22, "dlr": 16, "dcc": 202, "dw": 328, "odnd": 225, "adnd": 213, "bx": 319, "dnd2e": 145, "3e": 250, "3.5": 981, "4e": 469, "5e": 93724, "1dnd": 26, "earthdawn": 12, "fate": 476, "feast": 5, "flexible": 21488, "fws": 11, "gurps": 309, "l5r": 94, "mcc": 6, "motw": 461, "mm3": 281, "numenera": 109, "pf2e": 6029, "pf1e": 2565, "swade": 356, "swd": 205, "sr3": 17, "sr4": 32, "sr5": 204, "sr6": 49, "starfinder": 756, "swrpg": 627, "swn": 18, "wod": 1639}, "timezone": {"americas": {"GMT-3": 674, "GMT-4": 2147, "GMT-5": 40485, "GMT-6": 15850, "GMT-7": 4969, "GMT-8": 12109, "GMT-9": 37}, "europe": {"GMT-1": 16, "GMT+0": 8627, "GMT+1": 6928, "GMT+2": 3864, "GMT+3": 1120}, "australia": {"GMT+8": 932, "GMT+9": 107, "GMT+9:30": 62, "GMT+10": 1287, "GMT+10:30": 38, "GMT+11": 293}}, "generated_time": "2024-06-30 23:59:59"}