{"data_start_date": "2021-05-20", "total_posts": 182897, "nsfw_status": {"sfw": 180179, "nsfw": 2718}, "flair": {"gmplw": 60416, "plw": 100093, "gmw": 21707}, "location": {"online": 166365, "online_and_offline": 2239, "offline": 14028}, "play_by_post": 8196, "one_shot": 20737, "identity": {"lfbtq": 40794, "fem": 694, "poc": 2771, "accessible": 600}, "vtt": {"roll20": 37713, "foundry": 17457, "fantasy_grounds": 8795, "tabletop_simulator": 2756, "talespire": 836, "tableplop": 125, "one_more_multiverse": 104, "owlbear_rodeo": 2945, "above_vtt": 216}, "day_of_week": {"monday": 26580, "tuesday": 24258, "wednesday": 25107, "thursday": 26234, "friday": 33470, "saturday": 44725, "sunday": 45539}, "game": {"40k": 1068, "bitd": 290, "brp": 367, "coc": 1872, "cofd": 310, "cyberpunk": 1714, "dlc": 22, "dlr": 16, "dcc": 286, "dw": 467, "odnd": 354, "adnd": 301, "bx": 454, "dnd2e": 210, "3e": 339, "3.5": 1351, "4e": 687, "5e": 131191, "1dnd": 190, "earthdawn": 17, "fate": 677, "feast": 36, "flexible": 32794, "fws": 11, "gurps": 465, "l5r": 101, "mcc": 9, "motw": 611, "mm3": 399, "numenera": 156, "pf2e": 9245, "pf1e": 3470, "swade": 382, "swd": 259, "sr3": 17, "sr4": 32, "sr5": 225, "sr6": 64, "starfinder": 1023, "swrpg": 838, "swn": 19, "wod": 2490}, "timezone": {"americas": {"GMT-3": 972, "GMT-4": 3049, "GMT-5": 58611, "GMT-6": 23132, "GMT-7": 6888, "GMT-8": 17098, "GMT-9": 52}, "europe": {"GMT-1": 28, "GMT+0": 12214, "GMT+1": 10272, "GMT+2": 5618, "GMT+3": 1540}, "australia": {"GMT+8": 1407, "GMT+9": 142, "GMT+9:30": 94, "GMT+10": 1974, "GMT+10:30": 58, "GMT+11": 464}}, "generated_time": "2026-02-25 00:00:02"}